ucla_plha/Untitled.ipynb
ucla_plha/__init__.py
ucla_plha/config.json
ucla_plha/geometry/__init__.py
ucla_plha/geometry/geometry.py
ucla_plha/ground_motion_models/__init__.py
ucla_plha/ground_motion_models/ask14.py
ucla_plha/ground_motion_models/bssa14.py
ucla_plha/ground_motion_models/cb14.py
ucla_plha/ground_motion_models/cy14.py
ucla_plha/ground_motion_models/test.ipynb
ucla_plha/liquefaction_models/__init__.py
ucla_plha/liquefaction_models/boulanger_idriss_2016.py
ucla_plha/liquefaction_models/cetin_et_al_2018.py
ucla_plha/liquefaction_models/idriss_boulanger_2012.py
ucla_plha/liquefaction_models/moss_et_al_2006.py
ucla_plha/liquefaction_models/ngl_smt_2024.py
ucla_plha/plha.py
ucla_plha/source_models/fault_source_models/ucerf3_fm31/fault_id.npy
ucla_plha/source_models/fault_source_models/ucerf3_fm31/rect_rjb.npy
ucla_plha/source_models/fault_source_models/ucerf3_fm31/rect_segment_id.npy
ucla_plha/source_models/fault_source_models/ucerf3_fm31/ruptures.gz
ucla_plha/source_models/fault_source_models/ucerf3_fm31/ruptures_segments.gz
ucla_plha/source_models/fault_source_models/ucerf3_fm31/tri_rjb.npy
ucla_plha/source_models/fault_source_models/ucerf3_fm31/tri_rrup.npy
ucla_plha/source_models/fault_source_models/ucerf3_fm31/tri_segment_id.npy
ucla_plha/source_models/fault_source_models/ucerf3_fm32/fault_id.npy
ucla_plha/source_models/fault_source_models/ucerf3_fm32/rect_rjb.npy
ucla_plha/source_models/fault_source_models/ucerf3_fm32/rect_segment_id.npy
ucla_plha/source_models/fault_source_models/ucerf3_fm32/ruptures.gz
ucla_plha/source_models/fault_source_models/ucerf3_fm32/ruptures_segments.gz
ucla_plha/source_models/fault_source_models/ucerf3_fm32/tri_rjb.npy
ucla_plha/source_models/fault_source_models/ucerf3_fm32/tri_rrup.npy
ucla_plha/source_models/fault_source_models/ucerf3_fm32/tri_segment_id.npy
ucla_plha/source_models/point_source_models/ucerf3_fm31_grid_sub_seis/node_index.npy
ucla_plha/source_models/point_source_models/ucerf3_fm31_grid_sub_seis/points.npy
ucla_plha-1.1.0.dist-info/METADATA
ucla_plha-1.1.0.dist-info/WHEEL
ucla_plha-1.1.0.dist-info/licenses/LICENSE
ucla_plha-1.1.0.dist-info/RECORD
