Metadata-Version: 2.4
Name: ucla_plha
Version: 1.1.0
Summary: A code for performing probabilistic liquefaction hazard analysis inside the hazard integral
License: LICENSE
License-File: LICENSE
Author: Meera L. Kota
Requires-Python: >=3.8,<4.0
Classifier: License :: Other/Proprietary License
Classifier: Programming Language :: Python :: 3
Classifier: Programming Language :: Python :: 3.8
Classifier: Programming Language :: Python :: 3.9
Classifier: Programming Language :: Python :: 3.10
Classifier: Programming Language :: Python :: 3.11
Classifier: Programming Language :: Python :: 3.12
Classifier: Programming Language :: Python :: 3.13
Classifier: Programming Language :: Python :: 3.14
Requires-Dist: importlib_resources (>0)
Requires-Dist: ngl_tools (>0)
Requires-Dist: numpy (>=1.22,<2.0)
Requires-Dist: scikit_learn (>0)
